metadoctor/.env
metadoctor/.ipynb_checkpoints/__init__-checkpoint.py
metadoctor/.ipynb_checkpoints/base-checkpoint.py
metadoctor/.ipynb_checkpoints/database-checkpoint.py
metadoctor/.ipynb_checkpoints/element-checkpoint.py
metadoctor/.ipynb_checkpoints/enumeration-checkpoint.py
metadoctor/.ipynb_checkpoints/model-checkpoint.py
metadoctor/.ipynb_checkpoints/settings-checkpoint.py
metadoctor/.ipynb_checkpoints/utils-checkpoint.py
metadoctor/__init__.py
metadoctor/base.py
metadoctor/database.py
metadoctor/element.py
metadoctor/enumeration.py
metadoctor/model.py
metadoctor/settings.py
metadoctor/utils.py
metadoctor-0.1.6.dist-info/WHEEL
metadoctor-0.1.6.dist-info/METADATA
metadoctor-0.1.6.dist-info/RECORD
