Metadata-Version: 2.1
Name: metadoctor
Version: 0.1.6
Summary: 
Author: arantesdv
Author-email: arantesdv@me.com
Requires-Python: >=3.9,<4.0
Classifier: Programming Language :: Python :: 3
Classifier: Programming Language :: Python :: 3.9
Requires-Dist: MarkupSafe (>=2.0.1,<3.0.0)
Requires-Dist: deta (>=1.0.1,<2.0.0)
Requires-Dist: passlib[bcrypt] (>=1.7.4,<2.0.0)
Requires-Dist: starlette (>=0.17.1,<0.18.0)
